Metadata-Version: 2.1
Name: moto-custom-solutions
Version: 0.0.1
Summary: Library of useful functions for custom solutions.
Home-page: https://github.com/motoinsight-data-ops/motolibrary
Author: Dylan Doyle 
Author-email: ddoyle@motoinsight.ca
License: UNKNOWN
Platform: UNKNOWN
Classifier: Programming Language :: Python :: 3
Classifier: License :: OSI Approved :: MIT License
Classifier: Operating System :: OS Independent
Requires-Python: >=3.6
